dash_prism/Action.py
dash_prism/Prism.py
dash_prism/__init__.py
dash_prism/icons.py
dash_prism/init.py
dash_prism/registry.py
dash_prism/utils.py
dash_prism-0.7.2.dist-info/METADATA
dash_prism-0.7.2.dist-info/WHEEL
dash_prism-0.7.2.dist-info/licenses/LICENSE
dash_prism-0.7.2.dist-info/RECORD
