Metadata-Version: 2.4
Name: dash_prism
Version: 0.7.2
Summary: Prism: Powerful multi-panel workspace manager for Plotly Dash
License: Apache-2.0
License-File: LICENSE
Keywords: dash,plotly,plotly-dash,dashboard,workspace,tabs,panels,layout,ui,components,drag-and-drop
Author: Ludwig Jonsson
Author-email: developer-prism@protonmail.com
Requires-Python: >=3.10,<4.0
Classifier: Development Status :: 4 - Beta
Classifier: Framework :: Dash
Classifier: Intended Audience :: Developers
Classifier: License :: OSI Approved :: Apache Software License
Classifier: Operating System :: OS Independent
Classifier: Programming Language :: Python :: 3
Classifier: Programming Language :: Python :: 3.10
Classifier: Programming Language :: Python :: 3.11
Classifier: Programming Language :: Python :: 3.12
Classifier: Programming Language :: Python :: 3.13
Classifier: Programming Language :: Python :: 3.14
Classifier: Topic :: Internet :: WWW/HTTP :: Dynamic Content
Classifier: Topic :: Scientific/Engineering :: Visualization
Classifier: Topic :: Software Development :: Libraries :: Python Modules
Requires-Dist: dash (>=3.1.1,<4.0.0)
Project-URL: Documentation, https://ludwigaj.github.io/dash-prism
Project-URL: Homepage, https://github.com/LudwigAJ/dash-prism
Project-URL: Repository, https://github.com/LudwigAJ/dash-prism.git
